deardir/__init__.py
deardir/cli.py
deardir/core.py
deardir-0.1.4.dist-info/LICENSE.md
deardir-0.1.4.dist-info/METADATA
deardir-0.1.4.dist-info/WHEEL
deardir-0.1.4.dist-info/entry_points.txt
deardir-0.1.4.dist-info/RECORD
