Metadata-Version: 2.3
Name: deardir
Version: 0.1.4
Summary: Validate and optionally create directory structures from YAML or JSON schema files.
License: MIT
Author: Dennis Weiß
Author-email: dellen2203@googlemail.com
Requires-Python: >=3.8,<4.0
Classifier: License :: OSI Approved :: MIT License
Classifier: Programming Language :: Python :: 3
Classifier: Programming Language :: Python :: 3.8
Classifier: Programming Language :: Python :: 3.9
Classifier: Programming Language :: Python :: 3.10
Classifier: Programming Language :: Python :: 3.11
Classifier: Programming Language :: Python :: 3.12
Classifier: Programming Language :: Python :: 3.13
Requires-Dist: pyyaml (>=6.0,<7.0)
Requires-Dist: toml (>=0.10.2,<0.11.0)
